{
  "demo_cthulhu": [
    {
      "id": "ct1"
    },
    {
      "id": "ct2"
    },
    {
      "id": "ct3"
    },
    {
      "id": "ct4"
    },
    {
      "id": "ct5"
    },
    {
      "id": "ct6"
    },
    {
      "id": "ct7"
    },
    {
      "id": "ct8"
    },
    {
      "id": "ct9"
    },
    {
      "id": "ct10"
    },
    {
      "id": "ct11"
    },
    {
      "id": "ct12"
    },
    {
      "id": "ct13"
    },
    {
      "id": "ct14"
    },
    {
      "id": "ct15"
    },
    {
      "id": "ct16"
    },
    {
      "id": "ct17"
    },
    {
      "id": "ct18"
    },
    {
      "id": "ct19"
    },
    {
      "id": "ct20"
    },
    {
      "id": "ct21"
    },
    {
      "id": "ct22"
    },
    {
      "id": "ct23"
    },
    {
      "id": "ct24"
    }
  ],
  "demo_urban_legend": [
    {
      "id": "ul1"
    },
    {
      "id": "ul2"
    },
    {
      "id": "ul3"
    },
    {
      "id": "ul4"
    },
    {
      "id": "ul5"
    },
    {
      "id": "ul6"
    },
    {
      "id": "ul7"
    },
    {
      "id": "ul8"
    },
    {
      "id": "ul9"
    },
    {
      "id": "ul10"
    },
    {
      "id": "ul11"
    },
    {
      "id": "ul12"
    },
    {
      "id": "ul13"
    },
    {
      "id": "ul14"
    },
    {
      "id": "ul15"
    },
    {
      "id": "ul16"
    },
    {
      "id": "ul17"
    },
    {
      "id": "ul18"
    },
    {
      "id": "ul19"
    },
    {
      "id": "ul20"
    },
    {
      "id": "ul21"
    },
    {
      "id": "ul22"
    },
    {
      "id": "ul23"
    },
    {
      "id": "ul24"
    },
    {
      "id": "ul25"
    }
  ]
}